rdomanager_oscplugin/__init__.py
rdomanager_oscplugin/exceptions.py
rdomanager_oscplugin/plugin.py
rdomanager_oscplugin/utils.py
rdomanager_oscplugin/v1/overcloud_validate.py
rdomanager_oscplugin/v1/overcloud_update.py
rdomanager_oscplugin/v1/baremetal.py
rdomanager_oscplugin/v1/overcloud_image.py
rdomanager_oscplugin/v1/overcloud_node.py
rdomanager_oscplugin/v1/undercloud.py
rdomanager_oscplugin/v1/__init__.py
rdomanager_oscplugin/v1/overcloud_deploy.py
rdomanager_oscplugin/v1/overcloud_netenv_validate.py
rdomanager_oscplugin/tests/base.py
rdomanager_oscplugin/tests/test_rdomanager_oscplugin.py
rdomanager_oscplugin/tests/__init__.py
rdomanager_oscplugin/tests/fakes.py
rdomanager_oscplugin/tests/test_utils.py
rdomanager_oscplugin/tests/v1/test_plugin.py
rdomanager_oscplugin/tests/v1/__init__.py
rdomanager_oscplugin/tests/v1/utils.py
rdomanager_oscplugin/tests/v1/overcloud_validate/__init__.py
rdomanager_oscplugin/tests/v1/overcloud_validate/test_overcloud_validate.py
rdomanager_oscplugin/tests/v1/overcloud_validate/fakes.py
rdomanager_oscplugin/tests/v1/undercloud/test_undercloud.py
rdomanager_oscplugin/tests/v1/overcloud_deploy/test_overcloud_deploy_validators.py
rdomanager_oscplugin/tests/v1/overcloud_deploy/test_overcloud_deploy.py
rdomanager_oscplugin/tests/v1/overcloud_deploy/__init__.py
rdomanager_oscplugin/tests/v1/overcloud_deploy/fakes.py
rdomanager_oscplugin/tests/v1/overcloud_netenv_validate/__init__.py
rdomanager_oscplugin/tests/v1/overcloud_netenv_validate/test_overcloud_netenv_validate.py
rdomanager_oscplugin/tests/v1/overcloud_netenv_validate/fakes.py
rdomanager_oscplugin/tests/v1/overcloud_update/test_overcloud_update.py
rdomanager_oscplugin/tests/v1/overcloud_update/__init__.py
rdomanager_oscplugin/tests/v1/overcloud_update/fakes.py
rdomanager_oscplugin/tests/v1/baremetal/test_baremetal.py
rdomanager_oscplugin/tests/v1/baremetal/__init__.py
rdomanager_oscplugin/tests/v1/baremetal/fakes.py
python_rdomanager_oscplugin-0.0.10.dist-info/DESCRIPTION.rst
python_rdomanager_oscplugin-0.0.10.dist-info/metadata.json
python_rdomanager_oscplugin-0.0.10.dist-info/WHEEL
python_rdomanager_oscplugin-0.0.10.dist-info/pbr.json
python_rdomanager_oscplugin-0.0.10.dist-info/RECORD
python_rdomanager_oscplugin-0.0.10.dist-info/entry_points.txt
python_rdomanager_oscplugin-0.0.10.dist-info/METADATA
python_rdomanager_oscplugin-0.0.10.dist-info/top_level.txt
python_rdomanager_oscplugin-0.0.10.dist-info/dependency_links.txt
