Metadata-Version: 2.0
Name: python-rdomanager-oscplugin
Version: 0.0.10
Summary: RDO Manager OSC plugin lib
Home-page: http://github.com/rdo-management/python-rdomanager-oscplugin.git
Author: Brad P. Crochet
Author-email: brad@redhat.com
License: Apache License, Version 2.0
Platform: UNKNOWN
Classifier: Environment :: Console
Classifier: Environment :: OpenStack
Classifier: Intended Audience :: Developers
Classifier: Intended Audience :: Information Technology
Classifier: Intended Audience :: System Administrators
Classifier: License :: OSI Approved :: Apache Software License
Classifier: Operating System :: OS Independent
Classifier: Programming Language :: Python
Classifier: Programming Language :: Python :: 2
Classifier: Programming Language :: Python :: 2.7
Classifier: Programming Language :: Python :: 3
Classifier: Programming Language :: Python :: 3.3
Classifier: Programming Language :: Python :: 3.4
Requires-Dist: pbr (>=0.6,!=0.7,<1.0)
Requires-Dist: Babel (>=1.3)
Requires-Dist: cliff (>=1.7.0)
Requires-Dist: ipaddress
Requires-Dist: ironic-discoverd (==1.1.0)
Requires-Dist: os-cloud-config
Requires-Dist: python-heatclient (>=0.3.0)
Requires-Dist: python-ironicclient (>=0.4.1)
Requires-Dist: python-openstackclient (>=1.0.0)
Requires-Dist: python-tuskarclient (>=0.1.17)
Requires-Dist: six (>=1.9.0)
Requires-Dist: tripleo-common
